{"annotations": [{"completed_by": {"username": "", "first_name": "", "last_name": "", "avatar": ""}, "result": [], "was_cancelled": false, "ground_truth": false, "created_at": "2023-03-27T12:16:37.081388Z", "updated_at": "2023-03-27T12:16:37.081388Z", "lead_time": 42.0, "prediction": {}, "parent_prediction": null, "parent_annotation": null}], "drafts": [], "predictions": [], "data": {"image": "repo://08d7187ca96ed47158413b44af853b147e83b48a/data/valid/images/800px-Fires_cross_a_hill_in_SoCal_October_2007_jpg.rf.2e814eead70b7ecd4050ef33e4a67ac4.jpg"}, "meta": {}}