{"annotations": [{"completed_by": {"username": "", "first_name": "", "last_name": "", "avatar": ""}, "result": [], "was_cancelled": false, "ground_truth": false, "created_at": "2023-03-27T17:32:13.950180Z", "updated_at": "2023-03-27T17:32:13.950180Z", "lead_time": 42.0, "prediction": {}, "parent_prediction": null, "parent_annotation": null}], "drafts": [], "predictions": [], "data": {"image": "repo://0c08250177adacbfe3aede1898dc8866d81989dc/data/train/images/dormfire_1_jpg.rf.f2ac31511673d81ac09c049d84e78dfe.jpg"}, "meta": {}}