{"annotations": [{"completed_by": {"username": "", "first_name": "", "last_name": "", "avatar": ""}, "result": [{"id": "fUMBQNwXYd", "type": "rectanglelabels", "value": {"x": 40.1294498381877, "y": 29.447852760736193, "width": 19.41747572815534, "height": 20.858895705521473, "rotation": 0, "rectanglelabels": ["squirrel"]}, "origin": "manual", "to_name": "image", "from_name": "label", "image_rotation": 0, "original_width": 309, "original_height": 163}, {"id": "mpcnsghQVF", "type": "rectanglelabels", "value": {"x": 51.779935275080916, "y": 50.92024539877301, "width": 9.70873786407767, "height": 27.607361963190186, "rotation": 0, "rectanglelabels": ["squirrel"]}, "origin": "manual", "to_name": "image", "from_name": "label", "image_rotation": 0, "original_width": 309, "original_height": 163}, {"id": "OQfuhKaYGs", "type": "rectanglelabels", "value": {"x": 40.77669902912621, "y": 57.05521472392638, "width": 6.472491909385113, "height": 7.361963190184049, "rotation": 0, "rectanglelabels": ["squirrel"]}, "origin": "manual", "to_name": "image", "from_name": "label", "image_rotation": 0, "original_width": 309, "original_height": 163}], "was_cancelled": false, "ground_truth": false, "created_at": "2023-03-27T11:36:51.245134Z", "updated_at": "2023-03-27T11:36:51.245134Z", "lead_time": 42.0, "prediction": {}, "parent_prediction": null, "parent_annotation": null}], "drafts": [], "predictions": [], "data": {"image": "repo://08d7187ca96ed47158413b44af853b147e83b48a/imgs/train/images\\pic (58).jpg"}, "meta": {}}